src/baud_gen.v
// Baud rate generator for UART communication
//converts system clock to 16x baud rate ticks

module baud_gen #(
    parameter CLK_FREQ  = 50_000_000,
    parameter BAUD_RATE = 9600
)(
    input  wire clk,
    input  wire rst,
    output reg  tick
);
    localparam TICKS = CLK_FREQ / (BAUD_RATE * 16);
    integer count;

    always @(posedge clk or posedge rst) begin
        if (rst) begin
            count <= 0;
            tick  <= 0;
        end else begin
            if (count == TICKS - 1) begin
                count <= 0;
                tick  <= 1;
            end else begin
                count <= count + 1;
                tick  <= 0;
            end
        end
    end
endmodule

tb/tb_baud_gen.v
//TB to test baud generator independently

`timescale 1ns/1ps

module tb_baud_gen;

    reg  clk, rst;
    wire tick;

    baud_gen #(
        .CLK_FREQ(1600),
        .BAUD_RATE(10)
    ) uut (
        .clk(clk),
        .rst(rst),
        .tick(tick)
    );

    initial clk = 0;
    always #5 clk = ~clk;

    initial begin
        $dumpfile("sim/dump.vcd");
        $dumpvars(0, tb_baud_gen);
        rst = 1;
        #30  rst = 0;
        #500 $finish;
    end

    initial begin
        $monitor("t=%0t | count=%0d | tick=%b", $time, uut.count, tick);
    end

endmodule

sim/dump.vcd
$date
	Mon Jun 15 12:53:21 2026
$end
$version
	Icarus Verilog
$end
$timescale
	1ps
$end
$scope module tb_baud_gen $end
$var wire 1 ! tick $end
$var reg 1 " clk $end
$var reg 1 # rst $end
$scope module uut $end
$var wire 1 " clk $end
$var wire 1 # rst $end
$var parameter 32 $ BAUD_RATE $end
$var parameter 32 % CLK_FREQ $end
$var parameter 64 & TICKS $end
$var reg 1 ! tick $end
$var integer 32 ' count [31:0] $end
$upscope $end
$upscope $end
$enddefinitions $end
$comment Show the parameter values. $end
$dumpall
b1010 &
b11001000000 %
b1010 $
$end
#0
$dumpvars
b0 '
1#
0"
0!
$end
#5000
1"
#10000
0"
#15000
1"
#20000
0"
#25000
1"
#30000
0"
0#
#35000
b1 '
1"
#40000
0"
#45000
b10 '
1"
#50000
0"
#55000
b11 '
1"
#60000
0"
#65000
b100 '
1"
#70000
0"
#75000
b101 '
1"
#80000
0"
#85000
b110 '
1"
#90000
0"
#95000
b111 '
1"
#100000
0"
#105000
b1000 '
1"
#110000
0"
#115000
b1001 '
1"
#120000
0"
#125000
1!
b0 '
1"
#130000
0"
#135000
0!
b1 '
1"
#140000
0"
#145000
b10 '
1"
#150000
0"
#155000
b11 '
1"
#160000
0"
#165000
b100 '
1"
#170000
0"
#175000
b101 '
1"
#180000
0"
#185000
b110 '
1"
#190000
0"
#195000
b111 '
1"
#200000
0"
#205000
b1000 '
1"
#210000
0"
#215000
b1001 '
1"
#220000
0"
#225000
1!
b0 '
1"
#230000
0"
#235000
0!
b1 '
1"
#240000
0"
#245000
b10 '
1"
#250000
0"
#255000
b11 '
1"
#260000
0"
#265000
b100 '
1"
#270000
0"
#275000
b101 '
1"
#280000
0"
#285000
b110 '
1"
#290000
0"
#295000
b111 '
1"
#300000
0"
#305000
b1000 '
1"
#310000
0"
#315000
b1001 '
1"
#320000
0"
#325000
1!
b0 '
1"
#330000
0"
#335000
0!
b1 '
1"
#340000
0"
#345000
b10 '
1"
#350000
0"
#355000
b11 '
1"
#360000
0"
#365000
b100 '
1"
#370000
0"
#375000
b101 '
1"
#380000
0"
#385000
b110 '
1"
#390000
0"
#395000
b111 '
1"
#400000
0"
#405000
b1000 '
1"
#410000
0"
#415000
b1001 '
1"
#420000
0"
#425000
1!
b0 '
1"
#430000
0"
#435000
0!
b1 '
1"
#440000
0"
#445000
b10 '
1"
#450000
0"
#455000
b11 '
1"
#460000
0"
#465000
b100 '
1"
#470000
0"
#475000
b101 '
1"
#480000
0"
#485000
b110 '
1"
#490000
0"
#495000
b111 '
1"
#500000
0"
#505000
b1000 '
1"
#510000
0"
#515000
b1001 '
1"
#520000
0"
#525000
1!
b0 '
1"
